fuzzyextractor/__init__.py
fuzzyextractor-0.0.1.dist-info/LICENSE
fuzzyextractor-0.0.1.dist-info/METADATA
fuzzyextractor-0.0.1.dist-info/WHEEL
fuzzyextractor-0.0.1.dist-info/top_level.txt
fuzzyextractor-0.0.1.dist-info/RECORD
